lazyplot/__init__.py
lazyplot/config.py
lazyplot/plot.py
lazyplot-0.1.7.dist-info/METADATA
lazyplot-0.1.7.dist-info/WHEEL
lazyplot-0.1.7.dist-info/licenses/LICENSE
lazyplot-0.1.7.dist-info/RECORD
