Metadata-Version: 2.3
Name: lazyplot
Version: 0.1.7
Summary: plot matplotlib graph easily
Author-email: hiroh <hirohata0116@gmail.com>
Requires-Python: >=3.8
Requires-Dist: matplotlib>=3.7.5
Requires-Dist: numpy>=1.24.4
Requires-Dist: pillow>=10.4.0
